source/__init__.py
source/CLI/__init__.py
source/CLI/main.py
source/TUI/__init__.py
source/TUI/about.py
source/TUI/app.py
source/TUI/index.py
source/TUI/loading.py
source/TUI/monitor.py
source/TUI/progress.py
source/TUI/record.py
source/TUI/setting.py
source/TUI/update.py
source/application/__init__.py
source/application/app.py
source/application/download.py
source/application/explore.py
source/application/image.py
source/application/request.py
source/application/video.py
source/expansion/__init__.py
source/expansion/browser.py
source/expansion/cleaner.py
source/expansion/converter.py
source/expansion/file_folder.py
source/expansion/namespace.py
source/expansion/truncate.py
source/module/__init__.py
source/module/extend.py
source/module/manager.py
source/module/model.py
source/module/recorder.py
source/module/settings.py
source/module/static.py
source/module/tools.py
source/module/translator.py
XHS_DOWNLOADER-0.1.0.dist-info/LICENSE
XHS_DOWNLOADER-0.1.0.dist-info/METADATA
XHS_DOWNLOADER-0.1.0.dist-info/WHEEL
XHS_DOWNLOADER-0.1.0.dist-info/top_level.txt
XHS_DOWNLOADER-0.1.0.dist-info/RECORD
